[
	{
		"values"	: {
						"team" : "db(footballTeam)",
						"leagues": "(list(set(list(footballTeam.league))))",
						"CL": "var.leagues",
						"True_or_False": "rand([True,False])"
		},
		"title_true_false"        : ["تیم `var.team.name` در لیگ `var.team.league` فعالیت میکند1" , "تیم `var.team.name` در لیگ `choose(var.CL, 1)` فعالیت میکند2" , "3" , "42"], 
		"title_multichoices"      : ["تیم `var.team.name` در کدام لیگ فعالیت میکند"],
		"title_writing"      	  : ["تیم `var.team.name` در کدام لیگ فعالیت میکند"],
		"answer_multichoices"	  : ["var.team.league"],
		"answer_writing"		  : ["var.team.league"],
		"answer_true_false"       : ["var.True_or_False"],
		"choices_multichoices"    : ["choose(var.CL, 3)"],
        "__usage"				  : ["contest"],
		"number"				  : 1,
		"__level"                 : 1
	},



	{
		"values"	: {
						"team" : "`db(footballTeam)`",
						"teams" : "`db(footballTeam[footballTeam.league != var.team.league],NOC)`",
						"teams_same" : "`db(footballTeam[footballTeam.league == var.team.league],NOC)`",
						"ans_cnt" : "`rand(range(1,4))`"
		},
		"title_selective"         : ["از بین گزینه های زیر کدام تیمها در لیگ `var.team.league` حضور دارد؟"],
		"title_multichoices"      : ["کدام یک از تیم های زیر در لیگ `var.team.league` حضور دارد؟"],
		"answer_multichoices"	  : ["var.team.name"],
		"answer_selective"		  : ["choose(var.teams_same.name, ans_cnt)"],
		"choices_multichoices"    : ["choose(var.teams.name, 4-ans_cnt)"],
		"choices_selective"       : ["choose(var.teams.name, 4-ans_cnt)"],
        "__usage"				  : ["contest"],
		"number"				  : 2,
		"__level"                 : 1
	},



	{
		"values"	: {
						"team1" : "`db(footballTeam)`",
						"team2" : "`db(footballTeam[footballTeam.league != var.team.league ])`",
						"teams": "`db(footballTeam[footballTeam.league != var.team.league ], 3)`",
						"ans_cnt" : "`rand(range(2,4))`"
		},
        "titles"	: ["xx"],
		"answer"	: ["`var.teams.name`"],
        "choices"	: ["`var.team1.name`"],
        "titles_fa"	: ["تیم هایی که در یک لیگ فعالیت دارند راانتخاب کنید"],
        "usage"		: ["contest"],
		"type"		: "selective",
		"number"	: 5
	},
	{
		"values"	: {
						"team1" : "`db(footballTeam)`",			
						"team" : "`db(footballTeam[footballTeam.league != var.team1.league], 1)`",
						"teams": "`db(footballTeam[footballTeam.league == var.team1.league], NOC)`"
		},
        "titles"	: ["xx"],
		"answer"	: ["`var.teams.name`"],
        "choices"	: ["`var.team.name`"],
        "titles_fa"	: ["تیم هایی که در لیگ `var.team1.league` فعالیت دارند را انتخاب کنید"],
        "usage"		: ["contest"],
		"type"		: "selective",
		"number"	: 6,
		"level"		: "``"
	}
]
