[
    {
        "data": [],
        "data_id": [],
        "number": 7,
        "titles": [
            "xx`"
        ],
        "titles_fa": [
            "لوگوی تیم Fulham کدام است"
        ],
        "choices": [
            "https://cdn.sofifa.org/teams/10/light/113876.png",
            "https://cdn.sofifa.org/teams/10/light/1596.png",
            "https://cdn.sofifa.org/teams/10/light/112115.png",
            "https://cdn.sofifa.org/teams/10/light/144.png"
        ],
        "answer": [
            "https://cdn.sofifa.org/teams/10/light/144.png"
        ],
        "choices_fa": [
            "https://cdn.sofifa.org/teams/10/light/113876.png",
            "https://cdn.sofifa.org/teams/10/light/1596.png",
            "https://cdn.sofifa.org/teams/10/light/112115.png",
            "https://cdn.sofifa.org/teams/10/light/144.png"
        ],
        "answer_fa": [
            "https://cdn.sofifa.org/teams/10/light/144.png"
        ],
        "answer_type": "image",
        "subtitle_type": "empty",
        "type": "multi_choice",
        "title": "xx`",
        "title_fa": "لوگوی تیم Fulham کدام است",
        "tags": [
            "footballTeam"
        ],
        "active": true,
        "_id": "5c0e6409ac0e161ac59d285b"
    },
    {
        "data": [],
        "data_id": [],
        "number": 7,
        "titles": [
            "xx`"
        ],
        "titles_fa": [
            "لوگوی تیم Fulham کدام است"
        ],
        "choices": [
            "https://cdn.sofifa.org/teams/10/light/1475.png",
            "https://cdn.sofifa.org/teams/10/light/73.png",
            "https://cdn.sofifa.org/teams/10/light/112115.png",
            "https://cdn.sofifa.org/teams/10/light/144.png"
        ],
        "answer": [
            "https://cdn.sofifa.org/teams/10/light/144.png"
        ],
        "choices_fa": [
            "https://cdn.sofifa.org/teams/10/light/1475.png",
            "https://cdn.sofifa.org/teams/10/light/73.png",
            "https://cdn.sofifa.org/teams/10/light/112115.png",
            "https://cdn.sofifa.org/teams/10/light/144.png"
        ],
        "answer_fa": [
            "https://cdn.sofifa.org/teams/10/light/144.png"
        ],
        "answer_type": "image",
        "subtitle_type": "empty",
        "type": "multi_choice",
        "title": "xx`",
        "title_fa": "لوگوی تیم Fulham کدام است",
        "tags": [
            "footballTeam"
        ],
        "active": true,
        "_id": "5c0e640eac0e161ac59d285c"
    },
    {
        "data": [],
        "data_id": [],
        "number": 7,
        "titles": [
            "xx`"
        ],
        "titles_fa": [
            "لوگوی تیم Real Betis کدام است"
        ],
        "choices": [
            "https://cdn.sofifa.org/teams/10/light/69.png",
            "https://cdn.sofifa.org/teams/10/light/39.png",
            "https://cdn.sofifa.org/teams/10/light/467.png",
            "https://cdn.sofifa.org/teams/10/light/449.png"
        ],
        "answer": [
            "https://cdn.sofifa.org/teams/10/light/449.png"
        ],
        "choices_fa": [
            "https://cdn.sofifa.org/teams/10/light/69.png",
            "https://cdn.sofifa.org/teams/10/light/39.png",
            "https://cdn.sofifa.org/teams/10/light/467.png",
            "https://cdn.sofifa.org/teams/10/light/449.png"
        ],
        "answer_fa": [
            "https://cdn.sofifa.org/teams/10/light/449.png"
        ],
        "answer_type": "image",
        "subtitle_type": "empty",
        "type": "multi_choice",
        "title": "xx`",
        "title_fa": "لوگوی تیم Real Betis کدام است",
        "tags": [
            "footballTeam"
        ],
        "active": true,
        "_id": "5c0e6413ac0e161ac59d285d"
    },
    {
        "data": [],
        "data_id": [],
        "number": 7,
        "titles": [
            "xx`"
        ],
        "titles_fa": [
            "لوگوی تیم FC Barcelona کدام است"
        ],
        "choices": [
            "https://cdn.sofifa.org/teams/10/light/111393.png",
            "https://cdn.sofifa.org/teams/10/light/112172.png",
            "https://cdn.sofifa.org/teams/10/light/111397.png",
            "https://cdn.sofifa.org/teams/10/light/241.png"
        ],
        "answer": [
            "https://cdn.sofifa.org/teams/10/light/241.png"
        ],
        "choices_fa": [
            "https://cdn.sofifa.org/teams/10/light/111393.png",
            "https://cdn.sofifa.org/teams/10/light/112172.png",
            "https://cdn.sofifa.org/teams/10/light/111397.png",
            "https://cdn.sofifa.org/teams/10/light/241.png"
        ],
        "answer_fa": [
            "https://cdn.sofifa.org/teams/10/light/241.png"
        ],
        "answer_type": "image",
        "subtitle_type": "empty",
        "type": "multi_choice",
        "title": "xx`",
        "title_fa": "لوگوی تیم FC Barcelona کدام است",
        "tags": [
            "footballTeam"
        ],
        "active": true,
        "_id": "5c0e6417ac0e161ac59d285e"
    },
    {
        "data": [],
        "data_id": [],
        "number": 7,
        "titles": [
            "xx`"
        ],
        "titles_fa": [
            "لوگوی تیم SD Eibar کدام است"
        ],
        "choices": [
            "https://cdn.sofifa.org/teams/10/light/481.png",
            "https://cdn.sofifa.org/teams/10/light/449.png",
            "https://cdn.sofifa.org/teams/10/light/110316.png",
            "https://cdn.sofifa.org/teams/10/light/467.png"
        ],
        "answer": [
            "https://cdn.sofifa.org/teams/10/light/467.png"
        ],
        "choices_fa": [
            "https://cdn.sofifa.org/teams/10/light/481.png",
            "https://cdn.sofifa.org/teams/10/light/449.png",
            "https://cdn.sofifa.org/teams/10/light/110316.png",
            "https://cdn.sofifa.org/teams/10/light/467.png"
        ],
        "answer_fa": [
            "https://cdn.sofifa.org/teams/10/light/467.png"
        ],
        "answer_type": "image",
        "subtitle_type": "empty",
        "type": "multi_choice",
        "title": "xx`",
        "title_fa": "لوگوی تیم SD Eibar کدام است",
        "tags": [
            "footballTeam"
        ],
        "active": true,
        "_id": "5c0e641cac0e161ac59d285f"
    }
]